reversion/__init__.py
reversion/admin.py
reversion/apps.py
reversion/errors.py
reversion/middleware.py
reversion/models.py
reversion/revisions.py
reversion/signals.py
reversion/views.py
reversion/locale/ar/LC_MESSAGES/django.mo
reversion/locale/ar/LC_MESSAGES/django.po
reversion/locale/cs/LC_MESSAGES/django.mo
reversion/locale/cs/LC_MESSAGES/django.po
reversion/locale/da/LC_MESSAGES/django.mo
reversion/locale/da/LC_MESSAGES/django.po
reversion/locale/de/LC_MESSAGES/django.mo
reversion/locale/de/LC_MESSAGES/django.po
reversion/locale/es/LC_MESSAGES/django.mo
reversion/locale/es/LC_MESSAGES/django.po
reversion/locale/es_AR/LC_MESSAGES/django.mo
reversion/locale/es_AR/LC_MESSAGES/django.po
reversion/locale/fr/LC_MESSAGES/django.mo
reversion/locale/fr/LC_MESSAGES/django.po
reversion/locale/he/LC_MESSAGES/django.mo
reversion/locale/he/LC_MESSAGES/django.po
reversion/locale/it/LC_MESSAGES/django.mo
reversion/locale/it/LC_MESSAGES/django.po
reversion/locale/nb/LC_MESSAGES/django.mo
reversion/locale/nb/LC_MESSAGES/django.po
reversion/locale/nl/LC_MESSAGES/django.mo
reversion/locale/nl/LC_MESSAGES/django.po
reversion/locale/pl/LC_MESSAGES/django.mo
reversion/locale/pl/LC_MESSAGES/django.po
reversion/locale/pt_BR/LC_MESSAGES/django.mo
reversion/locale/pt_BR/LC_MESSAGES/django.po
reversion/locale/ru/LC_MESSAGES/django.mo
reversion/locale/ru/LC_MESSAGES/django.po
reversion/locale/sk/LC_MESSAGES/django.mo
reversion/locale/sk/LC_MESSAGES/django.po
reversion/locale/sl_SI/LC_MESSAGES/django.mo
reversion/locale/sl_SI/LC_MESSAGES/django.po
reversion/locale/sv/LC_MESSAGES/django.mo
reversion/locale/sv/LC_MESSAGES/django.po
reversion/locale/uk/LC_MESSAGES/django.mo
reversion/locale/uk/LC_MESSAGES/django.po
reversion/locale/zh_Hans/LC_MESSAGES/django.mo
reversion/locale/zh_Hans/LC_MESSAGES/django.po
reversion/management/__init__.py
reversion/management/commands/__init__.py
reversion/management/commands/createinitialrevisions.py
reversion/management/commands/deleterevisions.py
django_reversion-5.0.12.dist-info/LICENSE
django_reversion-5.0.12.dist-info/METADATA
django_reversion-5.0.12.dist-info/WHEEL
django_reversion-5.0.12.dist-info/top_level.txt
django_reversion-5.0.12.dist-info/RECORD
