Metadata-Version: 2.1
Name: django-reversion
Version: 5.0.12
Summary: An extension to the Django web framework that provides version control for model instances.
Home-page: https://github.com/etianen/django-reversion
Author: Dave Hall
Author-email: dave@etianen.com
License: BSD
Classifier: Development Status :: 5 - Production/Stable
Classifier: Environment :: Web Environment
Classifier: Intended Audience :: Developers
Classifier: License :: OSI Approved :: BSD License
Classifier: Operating System :: OS Independent
Classifier: Programming Language :: Python
Classifier: Programming Language :: Python :: 3.7
Classifier: Programming Language :: Python :: 3.8
Classifier: Programming Language :: Python :: 3.9
Classifier: Programming Language :: Python :: 3.10
Classifier: Programming Language :: Python :: 3.11
Classifier: Framework :: Django
Requires-Python: >=3.7
License-File: LICENSE
Requires-Dist: django>=3.2
